{"version":1,"resource":"vscode-remote://ssh-remote%2Bec2-user/home/ec2-user/myAuth/urls.py","entries":[{"id":"NIne.py","timestamp":1664450943021},{"id":"pLDG.py","timestamp":1664450955309},{"id":"nRjC.py","timestamp":1664453716576},{"id":"4Skv.py","timestamp":1664453736324},{"id":"GEOW.py","source":"undoRedo.source","timestamp":1664453781091},{"id":"yiRP.py","timestamp":1664453836478},{"id":"JimU.py","timestamp":1664453847302},{"id":"exgu.py","timestamp":1664453916213},{"id":"k3a6.py","timestamp":1664454729704},{"id":"vCGQ.py","timestamp":1664455048418},{"id":"VBnB.py","timestamp":1664455065962},{"id":"1Zzh.py","timestamp":1664455081466},{"id":"t1xZ.py","timestamp":1664455108993},{"id":"1j0c.py","timestamp":1664455122785},{"id":"4dbS.py","timestamp":1664455216300},{"id":"WnNb.py","timestamp":1664455269587},{"id":"ZSoU.py","timestamp":1664455358425},{"id":"FH0m.py","source":"undoRedo.source","timestamp":1664550315710}]}